meizi/__init__.py
meizi/cli.py
meizi/download.py
meizi/templates/base.html
meizi/templates/detail.html
meizi/templates/list.html
meizi/wsgi.py
meizi-0.1.4.dist-info/entry_points.txt
meizi-0.1.4.dist-info/METADATA
meizi-0.1.4.dist-info/WHEEL
meizi-0.1.4.dist-info/RECORD
