Metadata-Version: 2.1
Name: meizi
Version: 0.1.4
Summary: 
Author: Meng Xiangzhuo
Author-email: aumo@foxmail.com
Requires-Python: >=3.8,<4.0
Classifier: Programming Language :: Python :: 3
Classifier: Programming Language :: Python :: 3.8
Classifier: Programming Language :: Python :: 3.9
Classifier: Programming Language :: Python :: 3.10
Classifier: Programming Language :: Python :: 3.11
Requires-Dist: click (>=8.1.3,<9.0.0)
Requires-Dist: flask (>=2.2.2,<3.0.0)
Requires-Dist: loguru (>=0.6.0,<0.7.0)
Requires-Dist: parsel (>=1.7.0,<2.0.0)
Requires-Dist: requests (>=2.28.1,<3.0.0)
